LICENSE
MANIFEST.in
README.md
setup.py
docs/Makefile
docs/conf.py
docs/index.rst
docs/installation.rst
docs/usage.rst
textprocessor/__init__.py
textprocessor/models.py
textprocessor/tests.py
textprocessor.egg-info/PKG-INFO
textprocessor.egg-info/SOURCES.txt
textprocessor.egg-info/dependency_links.txt
textprocessor.egg-info/requires.txt
textprocessor.egg-info/top_level.txt
textprocessor/templatetags/__init__.py
textprocessor/templatetags/text_enhancer.py