Metadata-Version: 1.1
Name: textprocessor
Version: 0.2.0
Summary: Templatetags and filter to process text (string) to enhance link (add
Home-page: http://github.com/jibaku/django-textprocessor
Author: Fabien Schwob
Author-email: UNKNOWN
License: BSD
Platform: UNKNOWN
Classifier: Development Status :: 3 - Alpha
Classifier: Environment :: Web Environment
Classifier: Intended Audience :: Developers
Classifier: License :: OSI Approved :: BSD License
Classifier: Operating System :: OS Independent
Classifier: Programming Language :: Python
Classifier: Framework :: Django
